pyllmlib/__init__.py
pyllmlib/chat.py
pyllmlib/config.py
pyllmlib/core.py
pyllmlib/prompts.py
pyllmlib/style.py
pyllmlib/providers/__init__.py
pyllmlib/providers/base.py
pyllmlib/providers/gemini.py
pyllmlib/providers/groq.py
pyllmlib/providers/mistral.py
pyllmlib/providers/openai.py
pyllmlib-0.1.1.dist-info/licenses/LICENSE
pyllmlib-0.1.1.dist-info/METADATA
pyllmlib-0.1.1.dist-info/WHEEL
pyllmlib-0.1.1.dist-info/top_level.txt
pyllmlib-0.1.1.dist-info/RECORD
