Metadata-Version: 2.4
Name: pyllmlib
Version: 0.1.1
Summary: A Simple Unified LLM API interface for OpenAI, Gemini, Mistral, Groq and more.
Home-page: https://github.com/yazirofi/pyllmlib
Author: Shay Yazirofi
Author-email: yazirofi@gmail.com
License: MIT
Project-URL: Documentation, https://github.com/yazirofi/pyllmlib#readme
Project-URL: Source Code, https://github.com/yazirofi/pyllmlib
Keywords: python genai llm api openai gemini mistral groq ai chatbot
Classifier: Development Status :: 4 - Beta
Classifier: Intended Audience :: Developers
Classifier: Programming Language :: Python :: 3
Classifier: Programming Language :: Python :: 3.7
Classifier: Programming Language :: Python :: 3.8
Classifier: Programming Language :: Python :: 3.9
Classifier: Programming Language :: Python :: 3.10
Classifier: Programming Language :: Python :: 3.11
Classifier: Topic :: Software Development :: Libraries
Requires-Python: >=3.7
License-File: LICENSE
Requires-Dist: requests>=2.20.0
Requires-Dist: rich>=13.0.0
Dynamic: author
Dynamic: author-email
Dynamic: classifier
Dynamic: description
Dynamic: description-content-type
Dynamic: home-page
Dynamic: keywords
Dynamic: license
Dynamic: license-file
Dynamic: project-url
Dynamic: requires-dist
Dynamic: requires-python
Dynamic: summary
